groupy/__init__.py
groupy/client.py
groupy/collations.py
groupy/exc.py
groupy/resources.py
groupy/servers.py
groupy/version.py
groupy-0.5.6.dist-info/LICENSE
groupy-0.5.6.dist-info/METADATA
groupy-0.5.6.dist-info/WHEEL
groupy-0.5.6.dist-info/top_level.txt
groupy-0.5.6.dist-info/RECORD
