Metadata-Version: 2.1
Name: groupy
Version: 0.5.6
Summary: Python client library for Grouper
Home-page: https://github.com/dropbox/groupy
Author: Gary M. Josack, Mark Smith, Herbert Ho, Luke Faraone, Russ Allbery
License: Apache-2.0
Platform: UNKNOWN
Classifier: Programming Language :: Python :: 2
Classifier: Programming Language :: Python :: 3
Classifier: Topic :: Software Development
Classifier: Topic :: Software Development :: Libraries
Classifier: Topic :: Software Development :: Libraries :: Python Modules
License-File: LICENSE
